predecon/__init__.py
predecon_exioreed-0.1.1.dist-info/LICENSE
predecon_exioreed-0.1.1.dist-info/METADATA
predecon_exioreed-0.1.1.dist-info/WHEEL
predecon_exioreed-0.1.1.dist-info/top_level.txt
predecon_exioreed-0.1.1.dist-info/RECORD
