Metadata-Version: 2.1
Name: predecon-exioreed
Version: 0.1.1
Summary: PreDeCon - An Implementation in Python, Compatible With Scikit-Learn
Home-page: https://github.com/exioReed/PreDeCon.git
Author: Maximilian Kaulmann
Author-email: exioreed@ownlink.eu
License: UNKNOWN
Platform: UNKNOWN
Classifier: Programming Language :: Python :: 3
Classifier: License :: OSI Approved :: MIT License
Classifier: Operating System :: OS Independent
Classifier: Intended Audience :: Science/Research
Classifier: Topic :: Scientific/Engineering
Requires-Python: >=3.6
Requires-Dist: joblib (>=0.14.0)
Requires-Dist: numpy (>=1.15.4)
Requires-Dist: scikit-learn (>=0.22.1)
